.gitignore
ArtisticLicense20.html
LICENSE
MANIFEST.in
README.md
callDocSphinx.sh
licenses-amendments.txt
setenv.sh
setup.cfg
setup.py
pysourceinfo/__init__.py
pysourceinfo/bininfo.py
pysourceinfo/fileinfo.py
pysourceinfo/helper.py
pysourceinfo/infolists.py
pysourceinfo/objectinfo.py
pysourceinfo.egg-info/PKG-INFO
pysourceinfo.egg-info/SOURCES.txt
pysourceinfo.egg-info/dependency_links.txt
pysourceinfo.egg-info/top_level.txt