Metadata-Version: 1.1
Name: pysourceinfo
Version: 0.1.28
Summary: The 'pysourceinfo' package provides utilities for simplified gain of runtime information related to source code locations. The information is mainly based on 'inspect', butextended where required.
Home-page: https://sourceforge.net/projects/pysourceinfo/
Author: Arno-Can Uestuensoez
Author-email: acue_sf2@sourceforge.net
License: Artistic-License-2.0 + Forced-Fairplay-Constraints
Download-URL: https://sourceforge.net/projects/pysourceinfo/files/
Keywords: Python Syntax Packages Modules Files Linenumbers Filenames Modulenames Packagenames RTTI PYTHONPATH inspect
Platform: any
Classifier: Development Status :: 3 - Alpha
Classifier: Intended Audience :: Developers
Classifier: License :: Free To Use But Restricted
Classifier: License :: OSI Approved :: Artistic License
Classifier: Natural Language :: English
Classifier: Operating System :: Microsoft :: Windows
Classifier: Operating System :: OS Independent
Classifier: Operating System :: POSIX :: BSD :: OpenBSD
Classifier: Operating System :: POSIX :: Linux
Classifier: Operating System :: MacOS :: MacOS X
Classifier: Operating System :: POSIX :: SunOS/Solaris
Classifier: Operating System :: POSIX
Classifier: Programming Language :: Python
Classifier: Programming Language :: Python :: 2
Classifier: Programming Language :: Python :: 2.7
Classifier: Programming Language :: Python :: 3
Classifier: Programming Language :: Python :: 3.5
Classifier: Programming Language :: Python :: 3.6
Classifier: Programming Language :: Unix Shell
Classifier: Topic :: Software Development :: Libraries :: Python Modules
Classifier: Topic :: Utilities
